CHANGES.txt
README.txt
bootstrap.py
buildout.cfg
setup.py
docs/DEVELOPER.txt
src/z3c/__init__.py
src/z3c.dobbin.egg-info/PKG-INFO
src/z3c.dobbin.egg-info/SOURCES.txt
src/z3c.dobbin.egg-info/dependency_links.txt
src/z3c.dobbin.egg-info/namespace_packages.txt
src/z3c.dobbin.egg-info/not-zip-safe
src/z3c.dobbin.egg-info/requires.txt
src/z3c.dobbin.egg-info/top_level.txt
src/z3c/dobbin/README.txt
src/z3c/dobbin/__init__.py
src/z3c/dobbin/bootstrap.py
src/z3c/dobbin/collections.py
src/z3c/dobbin/configure.zcml
src/z3c/dobbin/factory.py
src/z3c/dobbin/interfaces.py
src/z3c/dobbin/mapper.py
src/z3c/dobbin/relations.py
src/z3c/dobbin/session.py
src/z3c/dobbin/soup.py
src/z3c/dobbin/testing.py
src/z3c/dobbin/tests.py
src/z3c/dobbin/utility.py
src/z3c/dobbin/zs2sa.py