Metadata-Version: 1.0
Name: z3c.dobbin
Version: 0.4.0
Summary: Relational object persistance framework
Home-page: UNKNOWN
Author: Malthe Borch, Stefan Eletzhofer and the Zope Community
Author-email: zope-dev@zope.org
License: ZPL
Keywords: zope orm persistence
Platform: UNKNOWN
Classifier: Programming Language :: Python
Classifier: Environment :: Web Environment
Classifier: Framework :: Zope3
